rcdss/__init__.py
rcdss/__main__.py
rcdss/dsscanner.py
rcdss/log.py
rcdss/rpsl.py
rcdss/stats.py
rcdss-0.9.dist-info/LICENSE
rcdss-0.9.dist-info/METADATA
rcdss-0.9.dist-info/WHEEL
rcdss-0.9.dist-info/entry_points.txt
rcdss-0.9.dist-info/top_level.txt
rcdss-0.9.dist-info/RECORD
