Metadata-Version: 2.1
Name: rcdss
Version: 0.9
Summary: RIPE NCC CDS Scanner
Home-page: https://github.com/ripe-ncc/rcdss
Author: Ondřej Caletka
Author-email: ondrej.caletka@ripe.net
Classifier: Development Status :: 4 - Beta
Classifier: Environment :: Console
Classifier: Intended Audience :: System Administrators
Classifier: Operating System :: POSIX :: Linux
Classifier: Programming Language :: Python :: 3.6
Classifier: Programming Language :: Python :: 3 :: Only
Classifier: Topic :: System :: Systems Administration
Requires-Python: >=3.6
License-File: LICENSE
Requires-Dist: dnspython (>=2.3.0)
Requires-Dist: cryptography
Requires-Dist: click
